microbar/__init__.py
microbar/microbar.py
microbar-0.3.1.dist-info/DESCRIPTION.rst
microbar-0.3.1.dist-info/METADATA
microbar-0.3.1.dist-info/RECORD
microbar-0.3.1.dist-info/WHEEL
microbar-0.3.1.dist-info/metadata.json
microbar-0.3.1.dist-info/top_level.txt
